{
  "version": "7",
  "dialect": "postgresql",
  "entries": [
    {
      "idx": 0,
      "version": "7",
      "when": 1773720528796,
      "tag": "0000_medical_masked_marvel",
      "breakpoints": true
    },
    {
      "idx": 1,
      "version": "7",
      "when": 1773721000000,
      "tag": "0001_add_organization_invites",
      "breakpoints": true
    },
    {
      "idx": 2,
      "version": "7",
      "when": 1773760000000,
      "tag": "0002_add_admin_dashboard",
      "breakpoints": true
    }
  ]
}